universalmodels/__init__.py
universalmodels/constants.py
universalmodels/fastchat.py
universalmodels/interface.py
universalmodels/mock_model.py
universalmodels/mock_tokenizer.py
universalmodels/wrappers/README.md
universalmodels/wrappers/dev_model.py
universalmodels/wrappers/hf_api_model.py
universalmodels/wrappers/openai_api_model.py
universalmodels/wrappers/wrapper_model.py
universalmodels-0.0.6.dist-info/LICENSE
universalmodels-0.0.6.dist-info/METADATA
universalmodels-0.0.6.dist-info/WHEEL
universalmodels-0.0.6.dist-info/top_level.txt
universalmodels-0.0.6.dist-info/RECORD
