Metadata-Version: 2.1
Name: universalmodels
Version: 0.0.6
Summary: A series of wrappers to allow for multiple AI model sources to behave as huggingface transformers models
Author-email: Matthew Pisano <matthewpisano14@gmail.com>
License: MIT License
Keywords: ai,transformers,openai,huggingface,adapter
Classifier: Programming Language :: Python :: 3
Classifier: Development Status :: 3 - Alpha
Classifier: Topic :: Scientific/Engineering :: Artificial Intelligence
Requires-Python: >=3.10
License-File: LICENSE
Requires-Dist: transformers ~=4.35
Requires-Dist: torch ~=2.1
Requires-Dist: openai ~=1.7
Requires-Dist: huggingface-hub ~=0.20.2
Provides-Extra: fastchat
Requires-Dist: fschat[model_worker,webui] >=0.2.34 ; extra == 'fastchat'
